[{"type": "click", "button": "Button.left", "pos": [2353, 1012], "delay": 0.0, "dist": "poisson", "min": 1.65, "max": 2.05, "click_dist": "poisson", "area": {"top_left": [2307, 977], "bottom_right": [2395, 1048], "center": [2351.0, 1012.5]}, "name": "Click left 1"}, {"type": "click", "button": "Button.left", "pos": [1916, 755], "delay": 0.4860854148864746, "dist": "poisson", "min": 0.5, "max": 0.7, "click_dist": "poisson", "area": {"top_left": [1879, 724], "bottom_right": [1943, 780], "center": [1911.0, 752.0]}, "name": "Click left 2"}]